shuk/__init__.py
shuk/datasets.py
shuk-0.0.1.dist-info/METADATA
shuk-0.0.1.dist-info/WHEEL
shuk-0.0.1.dist-info/top_level.txt
shuk-0.0.1.dist-info/RECORD
